Workbook

Sheet Summary
A1: DfE Digital and Technology Standards - Compliance Summary
A3: How to Use:
A4: 1. In each standard sheet, set the RAG Rating column (D) to: Red, Amber, Green, or Met
A5: 2. This summary will automatically calculate the overall compliance for each standard
A6: 3. Core Standards (marked *) should be met by 2030 - these are: Broadband, Wireless Network, Network Switching, Digital Leadership, Filtering & Monitoring, Cyber Security
A8: Standard | B8: Total Recs | C8: Met | D8: Green | E8: Amber | F8: Red | G8: Not Set | H8: Overall Status
A9: Broadband * | B9: 3 | C9: =COUNTIF(Broadband!D5:D7,"Met") -> 0 | D9: =COUNTIF(Broadband!D5:D7,"Green") -> 0 | E9: =COUNTIF(Broadband!D5:D7,"Amber") -> 0 | F9: =COUNTIF(Broadband!D5:D7,"Red") -> 0 | G9: =B9-C9-D9-E9-F9 -> 3 | H9: =IF(F9>0,"Red",IF(E9>0,"Amber",IF(C9=B9,"Complete",IF(C9+D9=B9,"Green","In Progress")))) -> In Progress
A10: Cloud Solution | B10: 5 | C10: =COUNTIF('Cloud Solution'!D5:D9,"Met") -> 0 | D10: =COUNTIF('Cloud Solution'!D5:D9,"Green") -> 0 | E10: =COUNTIF('Cloud Solution'!D5:D9,"Amber") -> 0 | F10: =COUNTIF('Cloud Solution'!D5:D9,"Red") -> 0 | G10: =B10-C10-D10-E10-F10 -> 5 | H10: =IF(F10>0,"Red",IF(E10>0,"Amber",IF(C10=B10,"Complete",IF(C10+D10=B10,"Green","In Progress")))) -> In Progress
A11: Cyber Security * | B11: 7 | C11: =COUNTIF('Cyber Security'!D5:D11,"Met") -> 0 | D11: =COUNTIF('Cyber Security'!D5:D11,"Green") -> 0 | E11: =COUNTIF('Cyber Security'!D5:D11,"Amber") -> 0 | F11: =COUNTIF('Cyber Security'!D5:D11,"Red") -> 0 | G11: =B11-C11-D11-E11-F11 -> 7 | H11: =IF(F11>0,"Red",IF(E11>0,"Amber",IF(C11=B11,"Complete",IF(C11+D11=B11,"Green","In Progress")))) -> In Progress
A12: Digital Accessibility | B12: 3 | C12: =COUNTIF('Digital Accessibility'!D5:D7,"Met") -> 0 | D12: =COUNTIF('Digital Accessibility'!D5:D7,"Green") -> 0 | E12: =COUNTIF('Digital Accessibility'!D5:D7,"Amber") -> 0 | F12: =COUNTIF('Digital Accessibility'!D5:D7,"Red") -> 0 | G12: =B12-C12-D12-E12-F12 -> 3 | H12: =IF(F12>0,"Red",IF(E12>0,"Amber",IF(C12=B12,"Complete",IF(C12+D12=B12,"Green","In Progress")))) -> In Progress
A13: Digital Leadership * | B13: 4 | C13: =COUNTIF('Digital Leadership'!D5:D8,"Met") -> 0 | D13: =COUNTIF('Digital Leadership'!D5:D8,"Green") -> 0 | E13: =COUNTIF('Digital Leadership'!D5:D8,"Amber") -> 0 | F13: =COUNTIF('Digital Leadership'!D5:D8,"Red") -> 0 | G13: =B13-C13-D13-E13-F13 -> 4 | H13: =IF(F13>0,"Red",IF(E13>0,"Amber",IF(C13=B13,"Complete",IF(C13+D13=B13,"Green","In Progress")))) -> In Progress
A14: Filtering and Monitoring * | B14: 4 | C14: =COUNTIF('Filtering and Monitoring'!D5:D8,"Met") -> 0 | D14: =COUNTIF('Filtering and Monitoring'!D5:D8,"Green") -> 0 | E14: =COUNTIF('Filtering and Monitoring'!D5:D8,"Amber") -> 0 | F14: =COUNTIF('Filtering and Monitoring'!D5:D8,"Red") -> 0 | G14: =B14-C14-D14-E14-F14 -> 4 | H14: =IF(F14>0,"Red",IF(E14>0,"Amber",IF(C14=B14,"Complete",IF(C14+D14=B14,"Green","In Progress")))) -> In Progress
A15: Laptops, Desktops, Tablets | B15: 4 | C15: =COUNTIF('Laptops, Desktops, Tablets'!D5:D8,"Met") -> 0 | D15: =COUNTIF('Laptops, Desktops, Tablets'!D5:D8,"Green") -> 0 | E15: =COUNTIF('Laptops, Desktops, Tablets'!D5:D8,"Amber") -> 0 | F15: =COUNTIF('Laptops, Desktops, Tablets'!D5:D8,"Red") -> 0 | G15: =B15-C15-D15-E15-F15 -> 4 | H15: =IF(F15>0,"Red",IF(E15>0,"Amber",IF(C15=B15,"Complete",IF(C15+D15=B15,"Green","In Progress")))) -> In Progress
A16: Network Cabling | B16: 3 | C16: =COUNTIF('Network Cabling'!D5:D7,"Met") -> 0 | D16: =COUNTIF('Network Cabling'!D5:D7,"Green") -> 0 | E16: =COUNTIF('Network Cabling'!D5:D7,"Amber") -> 0 | F16: =COUNTIF('Network Cabling'!D5:D7,"Red") -> 0 | G16: =B16-C16-D16-E16-F16 -> 3 | H16: =IF(F16>0,"Red",IF(E16>0,"Amber",IF(C16=B16,"Complete",IF(C16+D16=B16,"Green","In Progress")))) -> In Progress
A17: Network Switching * | B17: 4 | C17: =COUNTIF('Network Switching'!D5:D8,"Met") -> 0 | D17: =COUNTIF('Network Switching'!D5:D8,"Green") -> 0 | E17: =COUNTIF('Network Switching'!D5:D8,"Amber") -> 0 | F17: =COUNTIF('Network Switching'!D5:D8,"Red") -> 0 | G17: =B17-C17-D17-E17-F17 -> 4 | H17: =IF(F17>0,"Red",IF(E17>0,"Amber",IF(C17=B17,"Complete",IF(C17+D17=B17,"Green","In Progress")))) -> In Progress
A18: Servers and Storage | B18: 4 | C18: =COUNTIF('Servers and Storage'!D5:D8,"Met") -> 0 | D18: =COUNTIF('Servers and Storage'!D5:D8,"Green") -> 0 | E18: =COUNTIF('Servers and Storage'!D5:D8,"Amber") -> 0 | F18: =COUNTIF('Servers and Storage'!D5:D8,"Red") -> 0 | G18: =B18-C18-D18-E18-F18 -> 4 | H18: =IF(F18>0,"Red",IF(E18>0,"Amber",IF(C18=B18,"Complete",IF(C18+D18=B18,"Green","In Progress")))) -> In Progress
A19: Wireless Network * | B19: 4 | C19: =COUNTIF('Wireless Network'!D5:D8,"Met") -> 0 | D19: =COUNTIF('Wireless Network'!D5:D8,"Green") -> 0 | E19: =COUNTIF('Wireless Network'!D5:D8,"Amber") -> 0 | F19: =COUNTIF('Wireless Network'!D5:D8,"Red") -> 0 | G19: =B19-C19-D19-E19-F19 -> 4 | H19: =IF(F19>0,"Red",IF(E19>0,"Amber",IF(C19=B19,"Complete",IF(C19+D19=B19,"Green","In Progress")))) -> In Progress
A20: IT Support | B20: 5 | C20: =COUNTIF('IT Support'!D5:D9,"Met") -> 0 | D20: =COUNTIF('IT Support'!D5:D9,"Green") -> 0 | E20: =COUNTIF('IT Support'!D5:D9,"Amber") -> 0 | F20: =COUNTIF('IT Support'!D5:D9,"Red") -> 0 | G20: =B20-C20-D20-E20-F20 -> 5 | H20: =IF(F20>0,"Red",IF(E20>0,"Amber",IF(OR(C20>0,D20>0,C20+D20=B20),IF(C20=B20,"Complete","Green"),"In Progress"))) -> In Progress
A21: TOTAL | B21: =SUM(B9:B20) -> 50 | C21: =SUM(C9:C20) -> 0 | D21: =SUM(D9:D20) -> 0 | E21: =SUM(E9:E20) -> 0 | F21: =SUM(F9:F20) -> 0 | G21: =SUM(G9:G20) -> 50
A23: Overall Completion: | B23: =ROUND((C21)/(B21)*100,1)&"%" -> 0%
A24: Core Standards Completion: | B24: =ROUND((SUM(C9+C11+C13+C14+C17+C19)/SUM(B9+B11+B13+B14+B17+B19))*100,1)&"%" -> 0%
A27: RAG Rating Guide:
A28: Met | B28: Standard fully implemented and compliant
A29: Green | B29: Good progress, minor gaps to address
A30: Amber | B30: Some progress, significant work needed
A31: Red | B31: Not started or major issues
A32: Complete | B32: All recommendations Met
A33: In Progress | B33: Mix of statuses

Sheet Report
A1: DfE Digital and Technology Standards - Compliance Status Report
A3: School/Organisation: | B3: [Enter your school name here] | E3: Report Date: | F3: 28/11/2025
A4: Prepared By: | B4: [Enter name and role]
A6: Executive Summary
A8: Overall Completion: | B8: =Summary!B22 -> 0 | D8: Core Standards Completion: | H8: =Summary!B23 -> 0%
A9: Target: All Core Standards to be Met by 2030
A11: Detailed Compliance Status
A13: Standard | B13: Total | C13: Met | D13: Green | E13: Amber | F13: Red | G13: Not Set | H13: Overall Status
A14: Broadband * | B14: =Summary!B9 -> 3 | C14: =Summary!C9 -> 0 | D14: =Summary!D9 -> 0 | E14: =Summary!E9 -> 0 | F14: =Summary!F9 -> 0 | G14: =Summary!G9 -> 3 | H14: =Summary!H9 -> In Progress
A15: Cloud Solution | B15: =Summary!B10 -> 5 | C15: =Summary!C10 -> 0 | D15: =Summary!D10 -> 0 | E15: =Summary!E10 -> 0 | F15: =Summary!F10 -> 0 | G15: =Summary!G10 -> 5 | H15: =Summary!H10 -> In Progress
A16: Cyber Security * | B16: =Summary!B11 -> 7 | C16: =Summary!C11 -> 0 | D16: =Summary!D11 -> 0 | E16: =Summary!E11 -> 0 | F16: =Summary!F11 -> 0 | G16: =Summary!G11 -> 7 | H16: =Summary!H11 -> In Progress
A17: Digital Accessibility | B17: =Summary!B12 -> 3 | C17: =Summary!C12 -> 0 | D17: =Summary!D12 -> 0 | E17: =Summary!E12 -> 0 | F17: =Summary!F12 -> 0 | G17: =Summary!G12 -> 3 | H17: =Summary!H12 -> In Progress
A18: Digital Leadership * | B18: =Summary!B13 -> 4 | C18: =Summary!C13 -> 0 | D18: =Summary!D13 -> 0 | E18: =Summary!E13 -> 0 | F18: =Summary!F13 -> 0 | G18: =Summary!G13 -> 4 | H18: =Summary!H13 -> In Progress
A19: Filtering and Monitoring * | B19: =Summary!B14 -> 4 | C19: =Summary!C14 -> 0 | D19: =Summary!D14 -> 0 | E19: =Summary!E14 -> 0 | F19: =Summary!F14 -> 0 | G19: =Summary!G14 -> 4 | H19: =Summary!H14 -> In Progress
A20: Laptops, Desktops, Tablets | B20: =Summary!B15 -> 4 | C20: =Summary!C15 -> 0 | D20: =Summary!D15 -> 0 | E20: =Summary!E15 -> 0 | F20: =Summary!F15 -> 0 | G20: =Summary!G15 -> 4 | H20: =Summary!H15 -> In Progress
A21: Network Cabling | B21: =Summary!B16 -> 3 | C21: =Summary!C16 -> 0 | D21: =Summary!D16 -> 0 | E21: =Summary!E16 -> 0 | F21: =Summary!F16 -> 0 | G21: =Summary!G16 -> 3 | H21: =Summary!H16 -> In Progress
A22: Network Switching * | B22: =Summary!B17 -> 4 | C22: =Summary!C17 -> 0 | D22: =Summary!D17 -> 0 | E22: =Summary!E17 -> 0 | F22: =Summary!F17 -> 0 | G22: =Summary!G17 -> 4 | H22: =Summary!H17 -> In Progress
A23: Servers and Storage | B23: =Summary!B18 -> 4 | C23: =Summary!C18 -> 0 | D23: =Summary!D18 -> 0 | E23: =Summary!E18 -> 0 | F23: =Summary!F18 -> 0 | G23: =Summary!G18 -> 4 | H23: =Summary!H18 -> In Progress
A24: Wireless Network * | B24: =Summary!B19 -> 4 | C24: =Summary!C19 -> 0 | D24: =Summary!D19 -> 0 | E24: =Summary!E19 -> 0 | F24: =Summary!F19 -> 0 | G24: =Summary!G19 -> 4 | H24: =Summary!H19 -> In Progress
A25: IT Support | B25: =Summary!B20 -> 5 | C25: =Summary!C20 -> 0 | D25: =Summary!D20 -> 0 | E25: =Summary!E20 -> 0 | F25: =Summary!F20 -> 0 | G25: =Summary!G20 -> 5 | H25: =Summary!H20 -> In Progress
A26: TOTAL | B26: =Summary!B21 -> 50 | C26: =Summary!C21 -> 0 | D26: =Summary!D21 -> 0 | E26: =Summary!E21 -> 0 | F26: =Summary!F21 -> 0 | G26: =Summary!G21 -> 50
A28: Core Standards (2030 Priority)
A29: The 6 Core Standards: Broadband, Wireless Network, Network Switching, Digital Leadership, Filtering & Monitoring, Cyber Security
A31: RAG Rating Key
A32: Met | B32: Fully implemented and compliant
A33: Green | B33: Good progress, minor gaps
A34: Amber | B34: Significant work needed
A35: Red | B35: Not started or major issues
A38: Notes:

Sheet Broadband
A2: Technical requirements to meet the standard | B2: Link to Standards
B3: https://www.gov.uk/guidance/meeting-digital-and-technology-standards-in-schools-and-colleges/broadband-internet-standards-for-schools-and-colleges
A4: DfE Recommendation | B4: Current Status & Notes | C4: Agilisys Recommendations | D4: RAG Rating | E4: Ownership
A5: Have full fibre broadband connection with appropriate speeds | B5: Full fibre services provide the capacity and speed needed for effective use of online learning tools. Getting the fastest speed you can afford enables teachers to make full use of online resources as integral parts of teaching and learning, saves money by using cloud-based solutions instead of on-site technical infrastructure, and provides flexibility to future proof schools as demand increases. Primary schools should have: Minimum 100Mbps download speed, Minimum 30Mbps upload speed. Secondary schools, all-through schools and FE colleges should have: Connection with capacity to deliver 1Gbps download and upload speed. Broadband should be provided using a full fibre connection (sometimes described as leased line or FTTP - Fibre to the Premises). Note: Copper connections do not meet this standard. You should implement this standard as soon as you can, usually at the end of any existing contract term or as soon as full fibre is available. Ensure any new contracts or extensions using non-full fibre types provide opportunity to change to fibre services when available. Speed may vary depending on: Internal network cabling and switches, Internal network equipment such as routers and wireless access points. See related standards on network cabling, switching and wireless.
A6: Build resilience into your broadband connection | B6: With increasing reliance on internet-based services, broadband internet is an essential service. You should ensure appropriate measures are in place to mitigate against a single point of failure. Resilient services should be implemented alongside, or as soon as possible after a new connection is installed. This standard requires a combination of: Multiple broadband connection services of different service types (for example, a leased line combined with FTTP or FTTP combined with low Earth orbit satellite), Multiple routers and appropriate associated router configuration to provide automatic failover to backup services as and when required, Redundant power options on core active network equipment. You should investigate which backup internet services are available and implement appropriate systems. Your broadband provider will be able to advise on possible solutions and costs. Primary and backup broadband connections must not be the same type as each other, ideally from different providers. This is important for business continuity because if primary connection fails, backup will take over as it's a separate connection.
A7: Have appropriate safeguarding measures in place | B7: It's essential that children are safeguarded from potentially harmful and inappropriate online material. An effective whole school approach to online safety empowers a school to protect and educate students and staff in their use of technology, and establishes ways to identify, intervene in, and escalate any concerns. You should already be meeting this standard as part of ongoing safeguarding requirements as set out in statutory safeguarding guidance on Keeping Children Safe in Education. You should talk to your supplier or in-house support team to ensure you have: A content filtering system in place which meets the requirements outlined in the online safety section of Keeping Children Safe in Education (paragraphs 123-135), A firewall as part of your internet and network system (this could be an on-premises device directly protecting your network and managed by the school, or an 'edge' service provided and managed by your supplier or in-house support team). See the Filtering and Monitoring standards for more detailed requirements on safeguarding measures.

Sheet Cloud Solution
A2: Technical requirements to meet the standard | B2: Link to Standards
B3: https://www.gov.uk/guidance/meeting-digital-and-technology-standards-in-schools-and-colleges/cloud-solution-standards-for-schools-and-colleges
A4: DfE Recommendation | B4: Current Status & Notes | C4: Agilisys Recommendations | D4: RAG Rating | E4: Ownership
A5: Use cloud solutions as an alternative to locally-hosted systems | B5: Using cloud solutions reduces the need for local servers and can: Support your overall school strategy, Allow you to take advantage of low-cost or free cloud services, Save money by reducing onsite equipment and energy costs and the need for support and licensing, Improve safety and security by increasing resilience to cyber attacks, Improve reliability and business continuity, Save time by allowing users to work more flexibly and collaboratively, Outsource hardware and software updating and maintenance. Many schools use a hybrid model with some cloud solutions running alongside onsite servers. The more cloud solutions you use, the more your school will benefit. Local servers may still be needed for some systems such as access control (door security), building management, or cashless catering. Before moving to cloud: Understand the software, devices and data you currently use and what you use them for, Consider the types of data you need to import and export easily from the cloud, Ask your IT support about free cloud services your school can benefit from. Use this information to assess where you can replace servers with cloud solutions including files, documents and shared folders. Cloud solutions need reliable broadband with capacity to support your needs - check you meet broadband internet, network switching, network cabling and wireless network standards. Training users will ensure they are confident using solutions correctly and help realise the benefits.
A6: Cloud solutions must follow data protection legislation | B6: You must comply with data protection legislation. Responsible bodies must seek assurance from cloud solution and IT support providers that data is being handled legally. Your IT support should consult with your DPO on data protection issues such as data retention and sharing. Your DPO should carry out Data Protection Impact Assessments (DPIA) for any cloud solutions that store personal and/or sensitive personal data (special category data). Check whether data you want to store and process in the cloud is personal and/or sensitive personal data. If so, you might need extra security measures such as encryption, password protection, or more restricted access. All systems must follow NCSC cloud security principles. Make sure: Data processing by third parties is covered by appropriate contract, There is a user account creation, approval and removal process that complies with data protection legislation, There is a data sharing agreement with your cloud solution provider, Roles and responsibilities for dealing with data breach are clearly documented. Data should be stored and processed in UK or EU, unless you have confirmed any international transfer complies with UK GDPR. Ask your provider about this. Your data sharing agreement needs to state that cloud solution provider will share information promptly if there is a data breach. This lets the data controller take necessary actions. You should already be meeting this standard in accordance with data protection legislation.
A7: Cloud solutions should use ID and access management tools | B7: Many cloud solutions work independently and need multiple logins and passwords. To meet data protection and safeguarding obligations, use a central ID and access management tool. This provides: One centrally managed account with one login for each user so users don't need multiple passwords, Simplified login organisation and management when users join or leave, Access management based on groups so right people get access to right tools. Make sure your IT support: Assesses your existing or potential cloud solutions and works with you to choose appropriate ID management system, The system is used to secure all current and future cloud solutions and systems (including curriculum tools). To meet this standard you should: Test it with all systems and make sure this is the only way staff and students can log on, Have agreed, documented processes in place to manage addition and removal of users, Create roles that ensure all types of users have right levels of access to right systems, Make sure your IT support has separate, secure access to your cloud solution, independent of the ID management system. You should meet this standard as soon as you can. It helps keep your data and systems secure. Check you meet the cyber security standards for schools and colleges.
A8: Cloud solutions should work on a range of devices and be available when needed | B8: Good access and availability will make it easy for users to work with data using different systems, from anywhere and from a range of devices. Poor or unreliable availability could have significant impact on running your school. Before entering cloud solutions agreement, make sure you understand how and when it will need to be accessed by users. When procuring cloud solutions make sure published availability targets meet your needs. Trial cloud solutions before committing to buy to ensure performance meets expectations. Availability targets may appear misleading. Cloud solutions run 24/7. Less than 1% difference in cloud availability can significantly affect downtime: 99% availability = approximately 7 hours downtime per month, 99.9% availability = approximately 45 minutes downtime per month, 99.99% availability = approximately 5 minutes downtime per month. To meet this standard: Make sure you can easily access data from cloud solution in a way which meets your and your users' needs, Allow easy but secure access from a range of devices, ask your cloud provider about secure access to their services, Make sure data used in cloud solution is portable and allows for: Secure encrypted transfer, Data export to open standard or commonly used format (e.g. CSV, ODT files), Data links through secure, documented APIs, Timely process for data transfer if you end the contract.
A9: Make sure that appropriate data backup provision is in place | B9: The most common risk of cloud data loss is accidental or deliberate data deletion by users. Although data loss by cloud providers is uncommon, it can happen. Loss of data can lead to data breach requiring notification to authorities, and may obstruct critical business operations. Cloud providers will only hold backup data for limited period (could be as little as 30 days). This depends on your service level agreement. Your DPO should know which data is critical and how long different types should be kept for. Working with your DPO and IT support, understand your cloud provider's backup processes and policies. Ask: What data do they backup? Where is it held (for UK GDPR compliance)? How long is data held for? How frequently are backups made? To meet this standard identify the data backup provision you need for each solution based on the data it will store. Consider: Its sensitivity, Its importance to normal operations, The impact if it were unavailable temporarily or permanently, How long you could be without the data before it becomes an issue, Balancing cost against need - frequent backups are more expensive so consider cost against age of data you recover from backup, For critical data use the 3-2-1 rule: at least 3 copies, on 2 devices and 1 offsite. Third party solutions and plug-ins are available for cloud solutions that don't meet your data backup needs. Discuss this with your cloud solution provider. You should already be meeting this standard to help safeguard, protect and secure your data and systems.

Sheet Cyber Security
A2: Technical requirements to meet the standard | B2: Link to Standards
B3: https://www.gov.uk/guidance/meeting-digital-and-technology-standards-in-schools-and-colleges/cyber-security-standards-for-schools-and-colleges
A4: DfE Recommendation | B4: Current Status & Notes | C4: Agilisys Recommendations | D4: RAG Rating | E4: Ownership
A5: Conduct a cyber risk assessment annually and review every term | B5: This is one of the 6 core standards to be met by 2030. Cyber incidents and attacks have significant operational and financial impacts. These incidents will often be an intentional and unauthorised attempt to access, change or damage data and digital technology. The SLT digital lead and IT support should: Review digital technology assets and any related cyber security risk, Check all digital technology is licensed, supported and updated, Complete a record of processing activities (ROPA) for all new and current systems storing or processing personal and sensitive personal data, Assess staff access and permissions to systems and data, and check password policies, Check email is set up to be secure and reduces risk of third parties sending imitation emails. Keep documentation on your network up to date including: Network diagrams, Changes that are made, Settings and IP addressing information, Level of logging required to help identify source of any cyber incident or attack. Understand the current risk by: Understanding what the greatest cyber risks are and their likelihood and impact, Capturing how many cyber incidents or attacks have already occurred, Identifying any student or staff behaviour that may expose the school to cyber incidents, Testing your cyber resilience using NCSC's online tool. Create a risk management process and cyber response plan: Create simple reporting structure for cyber risks to be captured, escalated and actioned, Capture cyber risks in the risk register and place into regularly tested business continuity plan, Maintain documentation in at least one or more diverse locations (cloud or hard copy), Flag any risks or issues to governors or trustees, Put a cyber response plan in place (condition of RPA cover). You should complete any risk assessments as soon as possible and repeat them every year or in the event of: Significant change to your network, systems or data, A cyber incident or attack, Changes to funding or support arrangements.
A6: Create and implement a cyber awareness plan for students and staff | B6: An acceptable use policy describes what a person on the network can or cannot do when using digital technology. Anyone who has access to the school or college network or data needs to be made aware of, and sign up to, the acceptable use policy including guests and supply teachers. The SLT digital lead should work with IT support, designated safeguarding lead and DPO to create and update the acceptable use policy. If you use a student contract, this should include relevant sections of the acceptable use policy. Training students and staff in cyber security is vital for maintaining safety and security. Cyber training should be given at least annually, or more regularly if there is a known cyber risk. Training is required for: Students, Staff, At least one current governor or trustee, Anyone else with a login who may need more focused training. Training should be age-appropriate and suited to your school's risks, but should generally include: Methods hackers use for tricking people including phishing, Password security, Online safety, Social engineering, Physical security of devices (not leaving laptops unlocked and unattended), Risks of using removable storage media such as USBs, Multi-factor authentication, How to report a cyber incident or attack, How to report a personal data breach, Data protection for all staff with enhanced training for those exposed to higher risk data.
A7: Secure digital technology and data with anti-malware and a firewall | B7: Firewall requirements: Protect digital technology with correctly configured boundary firewall or software firewall including protection against denial of service attacks, Keep boundary firewall firmware up to date on supported versions (checked termly), Make sure all external connections to network run through the firewall, Change default administrator password and restrict remote access to only those who need it, Protect access with multi-factor authentication where available and prevent access from internet except to those maintaining the firewall, Actively monitor firewall traffic and switch on firewall alerts to detect suspicious activity, Block inbound unauthenticated connections by default, Document and review why inbound traffic has been permitted through firewall (termly minimum with SLT digital lead sign-off), Keep firewall rules to absolute minimum with each rule documented and subject to risk assessment, Enable software firewall for digital technology used outside of school such as at home or on public wifi, Consider VPN to encrypt data sent and received by a device. Anti-Malware Software should: Scan web pages as they are being used, Have centralized monitoring console to allow IT support to intervene if anti-malware fails or doesn't update, Scan files and applications upon access when downloaded or opened locally or from network folder, Scan attachments on incoming and outgoing emails for malware, Send malware alerts to IT support who will investigate, Prevent access to potentially malicious websites. Security Checks: Check downloads for malware before individuals can store or install them, Check and approve all current and future applications to ensure they don't pose security risk, Maintain current list of approved applications on contracts register, Remove unnecessary software according to organizational need, Only install applications that can be verified as coming from known supplier, Document how digital technology is set up including which security features are enabled or disabled, Review and manage browser settings to ensure highest protection is enabled and users cannot change settings to install extensions or bypass security, Check email is setup to be secure and reduces risk of third parties sending imitation emails.
A8: Control and secure user accounts and access privileges | B8: Passwords: IT support should: Enforce password strength at system level (NCSC suggest machine generated passwords or three random word system), Immediately change any passwords that have been compromised or suspected of compromise, Protect all passwords (allow no more than 10 guesses in 5 minutes, or lock devices after no more than 10 unsuccessful attempts). On networking devices and servers: Use password or PIN of at least 6 characters to physically access network switches and boot-up settings (password must only be used for this device), Agree process with SLT on securing access to key system passwords and PINs in event of emergency or if IT support unavailable. For younger children, users with SEND, or those with English as additional language, consider: Other means of logging on other than passwords (e.g. PIN code), Separate account accessed by teacher using student's login so student can still be identified (should follow filtering and monitoring standards). Multi-Factor Authentication (MFA) should include at least 2 of: Password, Text message with code to mobile device (staff only), Automated phone call with code, Secure portable device such as mobile phone or tablet for staff, Security key or device used to authenticate logins, Known or trusted account where second party authenticates another's credentials, Biometric test (may need biometric policy depending on data storage). Account Management: IT support should: Disable accounts as soon as someone leaves, Create and manage process with HR and finance team to deal with joiners, leavers, and role changes, Consider tools that link to MIS to automatically create or delete user accounts, Make sure accounts are set up so users only have access to data and systems they need, Apply MFA to any accounts and cloud-based applications for staff working remotely, Disable remote access when not required and enable only by authorized staff, Use enhanced security such as MFA where staff handle confidential, personal or sensitive personal data, Review accounts with finance team every term to identify missed changes, Ensure global or administrative accounts are not used for routine business, Agree process for handling administrative accounts so SLT or trustee approves changes before IT support can action, Make sure SLT have access to dedicated administrative account for emergencies.
A9: License digital technology and keep it up to date | B9: Licensing: All software needs to be licensed and eligible for security updates. You should remove unlicensed software or take steps to license it. IT support should check that: Operating systems and firmware on digital technology are kept up to date, Updates are issued in timely manner that doesn't impact teaching and learning, License expiry dates are recorded in contracts register by business professionals or finance team and unlicensed software is removed, Business professionals or finance team have been informed about license end dates so they can budget for renewal costs, Digital technology end-of-support dates are captured in asset register. Security Updates: IT support must complete security updates (patching) to operating systems, applications and firmware including configuration changes within 14 days of release where vulnerability is: Described as high risk or worse, Has Common Vulnerability Scoring System (CVSSv3) score of 7 or above. The CVSSv3 is security industry standard for measuring danger of a vulnerability. Score is number from 1 to 10 where 10 means most easily exploitable. IT support also needs to: Make sure security updates are applied on time (consider using supported third-party patch management tool to automate), Isolate devices where high risk patches are unavailable (remove from network or separate from higher risk systems and data). Occasionally DfE may issue instructions on security updates. SLT digital lead will inform IT support. IT support should then apply these updates within 5 working days of notification. An alternative to licensing software is to use cloud service. These are usually subscription based and supplier is responsible for licensing and updating. You should ask your DPO to undertake DPIA if storing or processing personal or sensitive personal data.
A10: Develop and implement a plan to back up your data and review this every year | B10: Analyse where you are now: It's useful to understand your current backup plan. SLT digital lead should ask IT support: What data is currently being backed up, how often, how old it is and how it's being backed up including data stored on all cloud services (store in information asset register using DfE information asset register template), What information is not being backed up, How often they test data restoration to check backups are successful, How long restoration will take and when last test restoration was completed, How many copies are being kept and where they are located, How your backups may be affected in event of incident or attack. Plan and action how to backup and restore your data: SLT digital lead should work with business professionals or finance team, designated safeguarding lead, DPO and IT support to identify: What data you backup including what critical data and systems are needed to function in disaster situation, How long you can go without specific systems and data and how up to date they need to be to determine priority of recovery, Process for students and staff to delete or archive data annually (speeds up recovery times). Make sure IT support understand: What critical data and systems are needed to function as school in disaster, What data needs to be backed up and where it's located including all cloud services, Who is responsible for backing up and maintaining backups, Where backed up data is held, including whether on-site, cloud, or combination, What system you will use to make sure backups are complete and working. Consider 3-2-1 rule for critical data: At least 3 copies of data, On at least 2 different types of storage media, At least 1 copy stored off-site or in cloud. Test backup and restoration processes regularly (at least annually) to ensure: Backups are complete and not corrupted, Restoration process works and data can be recovered, Recovery time objectives can be met, Staff know their roles in backup and recovery process.
A11: Report cyber attacks | B11: When to report: You should report cyber incidents and attacks when they: Result in unauthorized access to systems or data, Cause disruption to school or college operations, Involve theft or loss of data, Could affect personal data (potential data breach), Are attempted ransomware attacks, Involve compromise of critical systems. Internal reporting: The SLT digital lead should: Have clear process for staff to report cyber incidents, Ensure all staff know how to report incidents, Document all cyber incidents in incident log, Inform relevant stakeholders including SLT, governors, DPO as appropriate, Assess impact and coordinate response, Review incidents to identify lessons learned. External reporting: You must report certain incidents to external bodies: Report to Information Commissioner's Office (ICO) within 72 hours if personal data breach, Report serious cyber incidents to National Cyber Security Centre (NCSC) via their reporting service, If you have RPA cover, report to DfE as per RPA conditions, Report to police if criminal activity is suspected, Report to Action Fraud for fraud or financially motivated cybercrime. The cyber response plan should include: Clear escalation procedures, Contact details for external reporting bodies, Decision tree for when to report externally, Template communications for different scenarios, Roles and responsibilities during incident response. After reporting: Follow up with external bodies as required, Implement remediation actions, Update risk assessments and security measures, Communicate with affected parties as appropriate, Document the incident and response for future reference.

Sheet Digital Accessibility
A2: Technical requirements to meet the standard | B2: Link to Standards
B3: https://www.gov.uk/guidance/meeting-digital-and-technology-standards-in-schools-and-colleges/digital-accessibility-standards
A4: DfE Recommendation | B4: Current Status & Notes | C4: Agilisys Recommendations | D4: RAG Rating | E4: Ownership
A5: Include digital accessibility in relevant strategies and policies | B5: Digital accessibility means making digital products, content and services accessible and usable for all. Everyone should be able to access the same information and use equipment, regardless of their needs and situation. 1 in 5 people have a disability in the UK, but accessibility applies to all. Include accessible digital technology in your wider policies and strategies. These could be your: Digital technology strategy, Curriculum policy, SEND policy, Safeguarding policies, Communication policies. Work with students, staff and parents to identify their digital accessibility needs. When reviewing your policies and strategies, SLT and digital lead should work with relevant groups such as: SEND leads, Special Educational Needs Coordinators (SENCo), Curriculum leads, IT support, Parent/carer representatives. SLT should identify which strategies and policies you need to review and how you'll include digital accessibility in them. When you next review those strategies and policies, include: The accessibility needs of the school or college community, How you intend to meet these needs (this could include using accessibility features on existing systems or implementing new tools and services), How you'll make all communications and content, including your school or college website, accessible. Make sure everyone knows how to use accessibility features to meet their needs and those of others. Digital accessibility should be actively addressed and included in your next policy and strategy review. When digital accessibility is included in policies and strategies, this can help you: Meet legal obligations under Equality Act 2010, Provide equity of access for as many people as possible, Support students with SEND to access curriculum more effectively, Create more inclusive learning environment, Reduce barriers to learning, communication and access to information.
A6: Hardware and software should support the use of accessibility features | B6: Digital accessibility features are often included in existing devices and operating systems. These features will remove barriers to accessing teaching, learning and school or college operations. SLT should make sure new and existing hardware, software and digital services: Are accessible or have accessibility features included, Can provide equity of access, Are set up to work with assistive technology and audio-visual equipment, Remain safe and secure when accessibility features are enabled (accessibility features should not be blocked by generic security policies), Consider accessibility needs when using IT in exams. SLT should work with those responsible for: IT support and your digital strategy (as key decision makers they should include digital accessibility in their technology strategy, procurement and support), Special educational needs and disabilities (to make sure any assistive technologies used are compatible with chosen hardware and software), Procurement including digital licensing (to make sure any hardware and software bought has digital accessibility as part of their design or features), Curriculum planning and delivery (to make sure all students can access curriculum with help of digital accessibility tools when needed), Supporting student welfare (to make sure students' needs are understood and used for procurement and training). You should provide training for staff when required to do so. Training should cover: How to use built-in accessibility features, How to support others in using them, Understanding of different accessibility needs, How to create accessible content and materials, Which assistive technologies are available and how to use them. Consider these standards when reviewing your digital technology: Laptops, desktops and tablets standards (devices should meet educational needs and support accessibility), Filtering and monitoring standards (systems should not unreasonably impact accessibility needs or block assistive technologies).
A7: Communications should be accessible to all | B7: Making communications accessible can support students, staff, parents, and carers. It can assist those with additional needs like special educational needs, disabilities, and English as an additional language (EAL). Websites should be accessible for everyone. Consider accessibility when commissioning or building a website. Website accessibility is a legal requirement under the Public Sector Bodies (Websites and Mobile Applications) Accessibility Regulations 2018. Websites should meet WCAG 2.1 AA standards as a minimum. You could look at alternative formats for all communications, including: Email attachments (ensure PDFs and documents are accessible), Text messages (keep language simple and clear), Social media posts (use alt text for images, captions for videos), School newsletters (offer in different formats if needed), Parent letters (consider translation services for EAL families), Student reports (ensure readable by screen readers), Learning materials (provide in multiple formats where appropriate). Additionally, you should make sure that: There is understanding of accessibility and its importance throughout the school or college, Staff are trained on accessibility and can write and access content in an accessible format, Staff know who to contact to help them make things accessible (this may be the SENCo, IT support or the SLT digital lead), Content is created with accessibility in mind from the start, not added as an afterthought. Best practices for accessible content: Use plain English and avoid jargon where possible, Use clear headings and structure in documents, Ensure good color contrast (minimum 4.5:1 for normal text), Provide text alternatives (alt text) for images, Make sure documents can be read by screen readers, Use accessible fonts and appropriate font sizes, Avoid using color alone to convey information, Ensure videos have captions and transcripts, Keep sentences and paragraphs short and clear, Use bullet points and lists to break up text. SLT should lead and include staff involved in digital communication and its content.

Sheet Digital Leadership
A2: Technical requirements to meet the standard | B2: Link to Standards
B3: https://www.gov.uk/guidance/meeting-digital-and-technology-standards-in-schools-and-colleges/digital-leadership-and-governance-standards
A4: DfE Recommendation | B4: Current Status & Notes | C4: Agilisys Recommendations | D4: RAG Rating | E4: Ownership
A5: Assign a senior leadership team (SLT) member to be responsible for digital technology | B5: This is one of the 6 core standards to be met by 2030. The SLT digital lead is the person in the senior leadership team who is responsible for digital technology. This role has strategic oversight of digital technology and ensures up-to-date information on the school's digital technology is available to support decision making. The SLT digital lead should: Have strategic oversight of digital technology across the school or college, Understand the needs of your school or college and how technology can support them, Be able to commission technology services that meet your needs, Understand current and future digital technology requirements, Be part of relevant meetings where digital technology is discussed (e.g. SLT meetings, governor meetings, budget planning), Be able to advise on digital technology matters and their implications, Report to your board of trustees or governing body on digital technology matters regularly, Work closely with IT support (whether internal or external), Coordinate with other key roles such as business manager, data protection officer, designated safeguarding lead. This role should be clearly defined in job descriptions and understood across the organization. The SLT digital lead needs appropriate time, resources and authority to carry out this role effectively. Governing bodies and proprietors should: Ensure the SLT digital lead has appropriate time and resources, Receive regular reports on digital technology matters, Understand the strategic importance of digital technology, Support investment in technology infrastructure and training, Challenge and scrutinize technology decisions appropriately. The SLT digital lead doesn't need to be a technical expert but should understand how technology supports the school's strategic aims and how to work effectively with IT support and other stakeholders.
A6: Keep registers relating to hardware and systems up to date | B6: By including digital technology in these documents, schools and colleges will know what contracts, digital technology and data they have, and when they need to be reviewed. Contracts Register should include but not limited to: Contract name and description, Supplier details and contact information, Contract start and end dates, Contract value and payment terms, Notice periods for termination or renewal, Service level agreements (SLAs), Key terms and conditions, Contract owner within school, Review dates, Any dependencies or related contracts. You can record your contracts using the DfE contracts register template. Commercial and procurement information should be updated by the business or finance team, and IT support should update technical information. This contract register must be kept up to date. Asset Register is a log of all physical digital technology and tools within the school and should detail: Device type (laptop, desktop, tablet, server, network equipment), Make and model, Serial number or asset tag, Location, Date of purchase, Warranty expiry date, End of support date, Assigned user (if applicable), Operating system and key software, Status (in use, spare, decommissioned). Information Asset Register should record: What data you hold, Where it is stored, Who has access to it, What it is used for, How long it should be retained, Its sensitivity level, Any processing activities, Legal basis for processing, Any data sharing arrangements. You can record your information assets using the DfE information asset register template. Keeping these registers up to date: Helps with budget planning and procurement, Supports cyber security by knowing what you have, Assists with compliance (data protection, software licensing), Enables effective disaster recovery planning, Helps identify what needs replacing or upgrading, Supports audits and inspections.
A7: Include digital technology within disaster recovery and business continuity plans | B7: Schools and colleges need to plan for how they will respond to significant disruption to their technology. This could be caused by: Cyber attacks or security incidents, Hardware failures, Natural disasters affecting buildings or infrastructure, Supplier or service provider failures, Power outages, Internet connection failures. The disaster recovery and business continuity plan should include: Clear definition of what a 'disaster' looks like for your school, Identification of critical systems and data needed to function, Recovery time objectives (how quickly systems need to be restored), Recovery point objectives (how much data loss is acceptable), Roles and responsibilities during an incident, Communication plans (internal and external), Alternative working arrangements if technology is unavailable, Supplier contact details and escalation procedures, Testing schedule for the plan. The SLT digital lead will be responsible for this standard but needs input from: Operational team (finance, IT support, estate management), Teaching and other admin staff to understand risks and actions to avoid them, Designated safeguarding lead (advise on safeguarding needs in event of disaster), Data protection officer (advice for mitigating data risks and emergency responses), Governors or trust leadership (review, support and challenge these plans and provide sign-off), Any outsourced services or suppliers (e.g. MIS, broadband, cloud services) to understand their protocols and include in plans. The plan should be: Documented and easily accessible (including offline copies), Tested regularly (at least annually) through desktop exercises or simulations, Reviewed and updated after any test or actual incident, Communicated to all relevant staff, Aligned with wider school business continuity planning. Consider dependencies: What systems depend on each other? What happens if specific systems are unavailable? What workarounds exist? What minimum technology is needed to continue teaching and learning?
A8: Have a digital technology strategy that is reviewed every year | B8: Schools and colleges should have a 2-year digital technology strategy in place. This should be reviewed at least once a year to ensure it remains relevant and aligned with the school's broader strategic aims. Your digital technology strategy should include: Vision for using digital technology in your school or college, How technology will support teaching, learning and school operations, Current state assessment (where you are now), Future requirements and priorities (where you want to be), Gap analysis (what needs to change), Budget and procurement plans, Timeline for implementation, Risk management approach, Success metrics and how you'll measure progress, Roles and responsibilities, Training and professional development needs. The strategy should address: Infrastructure (broadband, networks, devices, servers), Software and cloud services, Cyber security and online safety, Data management and protection, Digital accessibility and inclusion, Staff and student digital skills, How technology supports curriculum delivery, Administrative and operational systems, Disaster recovery and business continuity, Sustainability and environmental impact. Creating the strategy: The SLT digital lead should lead the development with input from: Teaching staff (understand how technology supports learning), IT support (technical feasibility and requirements), Business/finance team (budget and value for money), SEND lead (accessibility requirements), Designated safeguarding lead (online safety), Data protection officer (data protection requirements), Students (their needs and experiences), Governors/trustees (strategic oversight and approval). Reviewing the strategy: Review at least annually or when: There are significant changes to school circumstances, New technologies become available, After major incidents or challenges, Following Ofsted or other inspections, When budgets change significantly, In response to changing educational requirements. The strategy should link to: School development plan, SEND strategy, Safeguarding policies, Teaching and learning policies, Data protection policies, Other relevant school strategies.

Sheet Filtering and Monitoring
A2: Technical requirements to meet the standard | B2: Link to Standards
B3: https://www.gov.uk/guidance/meeting-digital-and-technology-standards-in-schools-and-colleges/filtering-and-monitoring-standards-for-schools-and-colleges
A4: DfE Recommendation | B4: Current Status & Notes | C4: Agilisys Recommendations | D4: RAG Rating | E4: Ownership
A5: Identify and assign roles and responsibilities to manage your filtering and monitoring systems | B5: The SLT is responsible for: Buying filtering and monitoring systems, Documenting decisions on what is blocked or allowed and why, Reviewing the effectiveness of your provision, Overseeing reports, Making sure all staff understand their role, are appropriately trained, follow policies and procedures, and act on reports and concerns. Senior leaders should work closely with governors or proprietors, the DSL and IT support in all aspects of filtering and monitoring. Your DSL should lead on safeguarding and online safety including: Checking relevant reports, Responding to safeguarding concerns identified by filtering and monitoring, Providing governors with assurance that systems are working effectively and reviewed regularly. Your IT support (in-house or third-party) have technical responsibility for: Maintaining filtering and monitoring systems, Providing filtering and monitoring reports, Completing actions following concerns or system checks. They should work with SLT and DSL to help buy systems, identify risk, carry out reviews and checks.
A6: Review your filtering and monitoring provision at least once a year | B6: A review should be carried out to identify current provision, gaps, and specific needs. You need to understand: How students' risk profile could inform your approach (age, SEND, EAL), What your filtering system currently blocks or allows, Technical limitations, Any outside safeguarding influences such as county lines, Any relevant safeguarding reports or serious incidents, The digital resilience of your students, Teaching requirements (RSHE, PSHE curriculum), How your school uses technology including BYOD and generative AI tools, What related policies are in place, What checks are currently taking place and how actions are handled, Any technical setup recommendations. Following system or equipment changes, you should seek assurance that all filtering and monitoring solutions will continue to work on all school-managed devices. The review should take place at least once every academic year or when: A safeguarding risk is identified, There is a change in working practice like remote access or BYOD, New technology is introduced, Major software updates occur, Changes to technical configuration of network and devices.
A7: Have an active and well-managed filtering system | B7: Your filtering provider must: Be a member of Internet Watch Foundation (IWF), Be signed up to Counter-Terrorism Internet Referral Unit (CTIRU), Regularly update blocklists based on information from IWF and CTIRU. Schools must ensure these blocklists are included and cannot disable them or remove items. Your filtering system should be active, up to date and applied to all: School-managed devices including those taken off-site, Unmanaged devices under BYOD schemes, Guests who have access to the school internet. Check with your provider that your filtering system: Identifies and appropriately filters all internet feeds including backup connections, Is appropriate for the age and ability of users, Is suitable for educational settings, Identifies multilingual web content, images, common misspellings and abbreviations, Provides alerts when web content of concern has been blocked, Blocks technologies that allow users to bypass filtering such as VPNs, proxy services and end-to-end encryption. Your filtering system should allow you to identify as a minimum: Device name or ID, IP address, and where possible the individual, Time and date of attempted access, The search term or content being blocked. Search engines should have safe search enabled by default or use a child-friendly search engine. Make sure users cannot download additional browsers or unauthorised plugins.
A8: Have effective monitoring strategies that meet the safeguarding needs of your school or college | B8: All staff should conduct in-person monitoring if in a room with students on devices, as part of wider classroom supervision. Technical monitoring solutions may be needed to reduce identified risks. Your monitoring plan should include how you will monitor students when using school-managed devices connected to the internet. This could include: Device monitoring using device management software, In-person monitoring in the classroom, Network monitoring using log files of internet traffic and web access. As a minimum, your monitoring plan should include weekly monitoring reports highlighting incidents. It should also include immediate reports when an incident is classed as high-risk, for example those of a malicious, technical or safeguarding nature. Make sure that everyone using your school's network knows that filtering and monitoring processes are in place. Technical monitoring systems should notify users that the device is being monitored. Your monitoring plan should include how you communicate with staff about accepted ways of responding to incidents including: How to deal with incidents, Who should lead on any actions, When incidents should be acted on in line with your school's policy. There should be a documented process for recording incidents that includes what action was taken and the outcomes. Device monitoring should ensure: Monitoring systems work as expected both on-site and off-site, Reporting on student device activity is provided, Staff receive safeguarding training including online safety, Safeguarding concerns are recorded and reported to the DSL, Monitoring data is in a format staff can understand, Users are identifiable to the school so concerns can be traced back to individuals.

Sheet Laptops, Desktops, Tablets
A2: Technical requirements to meet the standard | B2: Link to Standards
B3: https://www.gov.uk/guidance/meeting-digital-and-technology-standards-in-schools-and-colleges/laptop-desktop-and-tablet-standards
A4: DfE Recommendation | B4: Current Status & Notes | C4: Agilisys Recommendations | D4: RAG Rating | E4: Ownership
A5: Make sure devices meet the needs of your school or college | B5: The SLT digital lead should assess how devices will support the needs of students and staff, based on the school's digital technology strategy. They should look at: How devices are being used, Who uses them, Where they are being kept, What they are being used for. This will help identify: The number of devices needed, The type of devices that are most suitable, Whether devices should be shared or allocated to individuals, How devices will be kept secure, How they will be maintained and supported. Consider how devices will support: Curriculum planning and delivery, Data and financial management, Flexible and cross-site working, Student needs based on age, curriculum, physical requirements and learning styles. The SLT digital lead should work with IT support to assess security and technical requirements of devices. This will help determine whether they need to buy new devices or if they can repurpose existing ones.
A6: Make sure devices are safe and secure | B6: Keep devices safe and secure to protect users, the network and data. This will: Make it easier to apply security and safeguarding policies, Reduce the risk of cyber incidents or attacks, Protect against loss or theft, Make it easier to manage devices centrally. IT support should work with the SLT digital lead to ensure all devices: Use anti-virus and anti-malware software as required, Use firewalls as required, Are connected to secure networks using VLANs where appropriate, Use device management systems, Have controls on what can be installed, Can be remotely wiped if lost or stolen, Are kept locked when not in use, Have security patches applied regularly. Devices should be reviewed once a year to take account of any changes to minimum requirements.
A7: Make sure devices meet or exceed the minimum requirements | B7: All devices should meet or exceed these minimum requirements: Operating Systems: Should be enterprise or education-grade, specifically designed for professional use (not Home versions). Support and Security Patches: New laptops and desktops should have 5 years of manufacturer support and security patches. New tablets should have 3 years of manufacturer support and security patches. Warranty: Laptops and desktops should have 3 years warranty. Tablets should have 2 years warranty. Wireless Connectivity: Devices should support the Wi-Fi standard 802.11ac Wave 2 as a minimum. It is recommended that devices meet Wi-Fi 6 (802.11ax). Screen Size: Tablet devices should have a minimum 9.7 inch screen. Devices should be reviewed at least once a year to take into account any changes to the minimum requirements set out in this standard. Laptops, desktops and tablets should be replaced or upgraded now if they do not meet the operating system requirements of this standard.
A8: Make sure devices are energy efficient, and they are bought and disposed of sustainably | B8: Taking an energy efficient approach to buying, setting up, using and disposal of devices will help with cost savings and sustainability. For existing devices: Switch off devices when not in use, Automatically power off when not needed out of hours, Only use the tools and software needed, Check existing devices before buying new ones to see if they can be repurposed. For new devices: All new devices should be rated with a low energy certification, Consider refurbished devices where appropriate. When disposing of devices you must: Meet Waste Electrical and Electronic Equipment (WEEE) regulations, Meet data protection requirements, Obtain certificates for WEEE disposal and destruction of data, Follow NCSC guidance on secure sanitisation of storage media, Update your IT asset register with any changes. The SLT digital lead should review the use of both existing and new devices. They should work with business professionals or the finance team to consider energy efficiency when investing in new devices.

Sheet Network Cabling
A2: Technical requirements to meet the standard | B2: Link to Standards
B3: https://www.gov.uk/guidance/meeting-digital-and-technology-standards-in-schools-and-colleges/network-cabling-standards-for-schools-and-colleges
A4: DfE Recommendation | B4: Current Status & Notes | C4: Agilisys Recommendations | D4: RAG Rating | E4: Ownership
A5: Use the right type and grade of cabling | B5: For copper cabling: Use Category 6A (Cat 6A) or better for all new installations. This supports speeds up to 10 Gigabit and is suitable for Power over Ethernet (PoE) applications. Cat 6A provides better performance and future-proofing than older standards. For optical fibre cabling: Use 16-core multi-mode OM4 fibre as a minimum for backbone connections between buildings or between floors. OM4 fibre supports 10 Gigabit speeds up to 400 metres. For longer distances over 400 metres, consider single-mode fibre which can support much longer runs. All cabling should: Meet manufacturer specifications and industry standards, Be properly terminated and tested after installation, Be suitable for current bandwidth needs and allow for future growth, Be installed in accordance with building regulations and fire safety requirements.
A6: Have cabling professionally installed with proper documentation | B6: Cabling installation should be carried out by qualified professionals who can: Follow manufacturer guidelines and industry best practices, Ensure proper cable management using appropriate trays and conduits, Maintain required separation from power cables to avoid interference, Test all cable runs after installation to verify performance, Provide certification that installation meets required standards. Documentation should include: Cable route plans showing where cables run, Labeling of all cables at both ends for easy identification, Testing certificates confirming performance, As-built drawings showing final installation, Location of patch panels and termination points. Good cable management: Allows for future additions and modifications, Protects cables from physical damage, Improves airflow in equipment rooms, Makes troubleshooting easier, Maintains the performance characteristics of the cabling.
A7: Plan for future cabling needs | B7: When installing or upgrading cabling: Consider future expansion and increased bandwidth requirements, Install spare capacity in cable trays and conduits, Use structured cabling approach with central patch panels, Document everything for future reference and troubleshooting, Consider the lifespan of the cabling (typically 15-20 years for copper). Future-proofing considerations: Allow for growth in number of devices, Plan for increased bandwidth demands, Consider emerging technologies like Wi-Fi 7, Leave space for additional cables in trays and conduits, Use higher grade cabling than minimum requirements where budget allows.

Sheet Network Switching
A2: Technical requirements to meet the standard | B2: Link to Standards
B3: https://www.gov.uk/guidance/meeting-digital-and-technology-standards-in-schools-and-colleges/network-switching-standards-for-schools-and-colleges
A4: DfE Recommendation | B4: Current Status & Notes | C4: Agilisys Recommendations | D4: RAG Rating | E4: Ownership
A5: Make sure switches meet performance requirements | B5: Network switches should provide: Minimum 1 Gigabit Ethernet ports for user connections to ensure adequate speed for modern applications and devices, 10 Gigabit uplink ports to core switches to prevent bottlenecks in the network backbone, Power over Ethernet (PoE) capability on switches where needed to power devices such as wireless access points, IP phones, and cameras without separate power supplies. Switches should have: Sufficient switching capacity (backplane bandwidth) to handle traffic from all ports simultaneously without bottlenecks, Support for Quality of Service (QoS) to prioritize critical traffic such as voice and video, VLAN capability to segment the network for security and performance, Support for jumbo frames if using applications that benefit from larger packet sizes. Consider future needs when sizing switches: Plan for growth in number of connected devices, Allow for increased bandwidth requirements, Consider consolidation opportunities.
A6: Have switches that can be centrally managed and monitored | B6: Switches should be managed devices (not unmanaged consumer switches) that provide: Central management capability through a network management system, SNMP (Simple Network Management Protocol) or equivalent monitoring to track performance and issues, Port-level control and monitoring to manage individual connections, Traffic monitoring capabilities to understand network usage patterns. Management features should include: Configuration backup and restore to protect against failures, Ability to update firmware centrally across multiple switches, Alert notifications for issues such as port failures or unusual traffic, Remote management access for IT support (with appropriate security), Port mirroring capability for network troubleshooting and monitoring. Centralized management: Reduces administrative overhead, Ensures consistent configuration across all switches, Makes troubleshooting faster and easier, Provides visibility into network performance.
A7: Secure network switches | B7: Network switches should have security features enabled including: Port security to prevent unauthorized devices connecting, DHCP snooping to prevent rogue DHCP servers, Dynamic ARP inspection to prevent ARP spoofing attacks, MAC address filtering where appropriate to control which devices can connect. Access control should include: Access Control Lists (ACLs) to control traffic flow, Secure management protocols (SSH instead of Telnet, HTTPS instead of HTTP), Changed default administrator credentials on all switches, Role-based access control for different administrative levels. Security maintenance requires: Regular security updates and firmware patches, Network segmentation using VLANs to isolate different types of traffic, Disabling unused ports to prevent unauthorized access, Regular security audits and configuration reviews, Documentation of security settings and changes.
A8: Build resilience into your switching infrastructure | B8: Network resilience features should include: Redundant power supplies in core and distribution switches to maintain operation if one power supply fails, Link aggregation to combine multiple connections for increased bandwidth and redundancy, Spanning Tree Protocol (STP) or equivalent to prevent network loops and provide automatic failover. For larger deployments consider: Switch stacking capability to manage multiple switches as a single unit, Redundant uplinks from distribution to core switches, Hot-swappable components to replace failed parts without downtime, Environmental monitoring for temperature and power issues. Resilience planning should: Identify single points of failure in the network, Have backup configurations stored securely off-site, Test failover procedures regularly, Document the network topology and dependencies, Have spare switches or components available for critical locations.

Sheet Servers and Storage
A2: Technical requirements to meet the standard | B2: Link to Standards
B3: https://www.gov.uk/guidance/meeting-digital-and-technology-standards-in-schools-and-colleges/servers-and-storage-standards-for-schools-and-colleges
A4: DfE Recommendation | B4: Current Status & Notes | C4: Agilisys Recommendations | D4: RAG Rating | E4: Ownership
A5: Build redundancy into servers and storage so your systems keep running | B5: Servers should have redundant components to avoid single points of failure: Redundant power supplies so server continues if one supply fails, RAID (Redundant Array of Independent Disks) configuration for storage so data remains accessible if a disk fails, Redundant network connections to maintain connectivity if one link fails. Additional resilience measures: Uninterruptible Power Supply (UPS) to keep servers running during power outages and allow graceful shutdown, Regular monitoring of hardware health to identify failing components before they cause outages, Predictive failure alerts from monitoring systems, Hot-swap capability to replace failed components without shutting down the server. Service agreements: Have Service Level Agreements (SLAs) with suppliers that specify response and repair times, Maintain support contracts that cover hardware replacement, Schedule regular maintenance windows for updates and testing, Test backup and recovery procedures regularly.
A6: Keep servers and storage secure | B6: Security requirements for servers: Use secure, supported operating systems that receive regular security updates, Apply security updates and patches promptly (within 14 days for high-risk vulnerabilities), Install and maintain anti-malware protection on all servers, Implement strong access controls and authentication (use Multi-Factor Authentication for administrative access). Data protection: Encrypt sensitive data both at rest and in transit, Implement comprehensive audit logging of access and changes, Use secure protocols for remote access (SSH, VPN, etc), Physical security measures to prevent unauthorized access to server hardware. Access management: Principle of least privilege - users should only have access they need, Separate administrative accounts from regular user accounts, Regular reviews of who has access to what, Disable or remove accounts when no longer needed, Strong password policies for all accounts. Security monitoring: Monitor logs for suspicious activity, Keep security software and definitions up to date, Regular security assessments and vulnerability scans, Incident response procedures documented and tested.
A7: Make servers and storage energy efficient | B7: Energy efficiency measures: Choose energy-efficient server hardware with good Energy Star or similar ratings, Use virtualization to consolidate multiple services onto fewer physical servers, Configure power management settings to reduce consumption during low usage, Implement efficient cooling systems in server rooms. Capacity planning: Regularly review server utilization to identify underused systems, Consolidate services where appropriate to reduce the number of physical servers, Right-size servers for their workload - don't over-provision, Monitor power usage to identify inefficient systems. Consider cloud alternatives: Evaluate whether cloud services could be more efficient and cost-effective for some workloads, Cloud providers typically have more efficient infrastructure at scale, Balance on-premises and cloud services based on needs. Lifecycle management: Decommission and properly dispose of unused or end-of-life servers, Keep an inventory of all servers and their purpose, Plan for regular refresh cycles, Dispose of equipment according to WEEE regulations.
A8: Make sure servers and storage are kept in a suitable environment | B8: Environmental requirements for server rooms: Temperature control: Maintain between 18-27°C for optimal equipment performance and longevity, Humidity control: Keep between 40-60% relative humidity to prevent static and condensation, Clean, stable power supply with protection against surges and outages, Adequate cooling systems sized for the heat load of the equipment. Physical security: Restricted access to authorized personnel only using access control systems, CCTV monitoring of server room entrances and interior if handling sensitive data, Fire suppression system appropriate for electronic equipment (not water-based), Environmental monitoring with alerts for temperature, humidity, water leaks. Layout and access: Proper equipment racks to organize servers and networking equipment, Adequate space for maintenance access around equipment, Good cable management to improve airflow and accessibility, Clear labeling of equipment and cables, Emergency procedures clearly posted, Maintenance lighting separate from always-on equipment lighting. Monitoring: Temperature and humidity sensors with alerting, Power monitoring to track usage and identify issues, Door access logging, Regular checks of environmental conditions.

Sheet IT Support
A1: IT Support Standards for Schools and Colleges
A3: Official DfE Guidance: | B3: https://www.gov.uk/guidance/meeting-digital-and-technology-standards-in-schools-and-colleges/it-support-standards-for-schools-and-colleges
A4: DfE Recommendation | B4: How to Meet the Standard | C4: Current Status / Notes | D4: RAG Rating | E4: Ownership
A5: 1. Make sure IT support helps you meet the digital and technology standards | B5: Your IT support team should have the necessary qualifications and experience to understand the standards and help your school or college meet them. Your SLT digital lead should assess whether your IT support needs any relevant professional memberships or certifications – for example, an Information Technology Infrastructure Library (ITIL) certification for individuals, or Cyber Essentials certification for companies. This may depend on the scale of your school or college's support needs. Your SLT digital lead should understand IT support's role in helping you meet the digital and technology standards.
A6: 2. Establish what IT support you need | B6: Your senior leadership team (SLT) digital lead should work with relevant staff, including your business manager and other SLT members to establish what IT support you need. This should include exceptional times such as the start of the academic year, exam periods or cyber security incidents. Consider: • Understanding the day-to-day technology needs of your staff and students • Making sure your technology supports teaching and learning • Aligning IT support with the needs of your digital technology strategy • Considering any planned technology upgrades and improvements IT support may be internal (staff members), external (third-party provider), or hybrid (mix of both).
A7: 3. Set clear expectations with your IT support service | B7: It's important to have clear expectations about how quickly issues are resolved, how they are prioritised and how they will be escalated. Set clear expectations for IT support's responsiveness to ensure capacity in times of high demand, for example during exam periods or at the start of the year. Requirements: • Clear expectations about issue resolution speed • Prioritization criteria for support requests • Escalation procedures • How support requests should be logged and managed • Capacity planning for peak periods
A8: 4. Establish effective logging and management of support requests | B8: There should be clear guidance about how support requests should be logged and managed. Requirements: • System for logging all support requests • Clear categorization and prioritization • Tracking of request status • Documentation of resolutions • Reporting capabilities for analysis This helps ensure: • Accountability for issue resolution • Visibility of support performance • Identification of recurring issues • Evidence for annual reviews
A9: 5. Review your IT support annually | B9: The guidance recommends an annual review as part of the organisation's strategy review as set out in the digital leadership and governance standard. The formal review should be led by the SLT digital lead and check: • What support you have • How well it's performing • Whether contracts and resources still offer value for money (value for money does not always mean the lowest cost!) The findings should be documented by the SLT digital lead and shared with SLT, the school business manager and governors or proprietors. This review helps ensure IT support continues to meet the school's evolving needs and strategic objectives.

Sheet Wireless Network
A2: Technical requirements to meet the standard | B2: Link to Standards
B3: https://www.gov.uk/guidance/meeting-digital-and-technology-standards-in-schools-and-colleges/wireless-network-standards-for-schools-and-colleges
A4: DfE Recommendation | B4: Current Status & Notes | C4: Agilisys Recommendations | D4: RAG Rating | E4: Ownership
A5: Make sure your wireless network meets performance requirements | B5: Wireless standard: Use Wi-Fi 6 (802.11ax) for all new access point deployments as it provides better performance, capacity and efficiency. Existing systems should meet at least 802.11ac Wave 2 standard as a minimum. Performance requirements: Adequate bandwidth to support the number of concurrent users in each area, Support for multiple SSIDs (network names) to separate different user groups, Band steering to automatically move devices to the best frequency (2.4GHz or 5GHz), Seamless roaming support so users can move around campus without disconnecting, Quality of Service (QoS) to prioritize important traffic like voice and video. Capacity planning: Design for peak usage scenarios not just average, Consider that many users now have multiple wireless devices, Plan for growth in number of devices and bandwidth requirements, Regular speed testing across all areas to verify performance. Modern Wi-Fi 6 features: Better handling of many devices in same area (important for classrooms), More efficient use of spectrum means faster speeds for all devices, Improved battery life for connected devices, Better performance in areas with interference.
A6: Make sure you have full wireless coverage across your school or college site | B6: Coverage requirements: Full wireless coverage in all teaching and learning spaces, Coverage in administrative and staff areas, Outdoor coverage in areas where devices will be used (courtyards, outdoor learning spaces), No dead zones where users cannot get signal. Signal quality: Minimum signal strength of -67 dBm or better in all areas where devices will be used, Overlap between access points to ensure smooth roaming, Consideration of building materials that may block or weaken signals (metal, concrete). Site survey: Conduct a professional wireless site survey before deployment to: Identify optimal access point locations, Determine how many access points are needed, Account for sources of interference, Plan for future expansion. Coverage testing: Regular testing after installation to verify coverage meets requirements, Test from user perspective at desk/seating height not just standing, Use heat mapping tools to visualize coverage, Re-test after any building changes or furniture moves, Capacity testing to ensure performance under load. High-density areas: Classrooms, halls, and assembly areas need special consideration for high device counts, May need multiple access points to serve one large space, Consider both coverage and capacity requirements.
A7: Make sure your wireless network is centrally managed | B7: Central management: Use a wireless controller (hardware or cloud-based) to manage all access points from single interface, Consistent configuration across all access points, Easy deployment of changes to all or selected access points, Centralized visibility into network performance and issues. Management capabilities: Configuration backup and restore to protect against failures and enable easy recovery, Push firmware updates to all access points simultaneously, Monitor performance and usage across the entire wireless network, User and device visibility to see who and what is connected, Traffic monitoring and reporting for capacity planning and troubleshooting. Additional features: Guest network capability for visitors without giving access to internal network, Rogue access point detection to identify unauthorized wireless networks, Automatic channel optimization to reduce interference, Centralized logging and alerting for security and troubleshooting. Cloud vs on-premises: Cloud management: Access from anywhere, automatic updates, typically subscription-based, On-premises controller: Local control, may require manual updates, typically capital expense, Choice depends on school's needs, IT capabilities and preferences.
A8: Make sure your wireless network is secure | B8: Encryption and authentication: Use WPA3 encryption for all new deployments (strongest available), Minimum WPA2 encryption for existing networks (WEP and WPA are no longer secure), Use 802.1X authentication with certificates for staff access (enterprise authentication), Pre-shared key for students if 802.1X not feasible, but rotate keys regularly. Network segmentation: Separate guest network that is isolated from internal network and cannot see other devices, Staff and student networks on different VLANs with appropriate access controls, Administrative management VLAN separate from user networks, IoT devices on separate network with restricted access. Security measures: Change all default passwords and administrative credentials, Disable old insecure protocols (WEP, WPA, WPS), Use strong passwords/passphrases for any pre-shared keys, Hide SSID broadcast if appropriate (though not a strong security measure alone), Disable rogue AP detection and alerting to identify unauthorized networks. Monitoring and auditing: Regular security audits of wireless configuration, Monitor for unauthorized access attempts, Keep access point firmware up to date with security patches, Review who has access and what they can access, MAC address filtering can be used but should not be relied on as primary security, Regular penetration testing of wireless security. Physical security: Secure access points to prevent tampering or theft, Place where difficult to access but still providing good coverage, Consider hardened access points for outdoor locations.
